django_walleter/__init__.py
django_walleter/exceptions.py
django_walleter/mixins.py
django_walleter/models.py
django_walleter/services.py
django_walleter/migrations/0001_initial.py
django_walleter/migrations/__init__.py
django_walleter-1.0.dist-info/METADATA
django_walleter-1.0.dist-info/WHEEL
django_walleter-1.0.dist-info/top_level.txt
django_walleter-1.0.dist-info/RECORD
