Metadata-Version: 2.1
Name: django-walleter
Version: 1.0
Summary: Django wallet
Home-page: https://github.com/Abdelhadi92/django_walleter
Author: Abdelhadi Abu-Shamleh
Author-email: abushamleh92@gmail.com
License: BSD
Keywords: Django wallet walleter
Platform: UNKNOWN
Classifier: Environment :: Web Environment
Classifier: Framework :: Django
Classifier: License :: OSI Approved :: BSD License
Classifier: Operating System :: OS Independent
Classifier: Development Status :: 5 - Production/Stable
Classifier: Programming Language :: Python
Classifier: Programming Language :: Python :: 3
Classifier: Programming Language :: Python :: 3.4
Classifier: Programming Language :: Python :: 3.5
Classifier: Programming Language :: Python :: 3.6
Classifier: Programming Language :: Python :: 3.7
Requires-Dist: setuptools
Requires-Dist: jsonfield
